pastelladmin/__init__.py
pastelladmin/chorus_check.py
pastelladmin/delete_any.py
pastelladmin/iparapheur_check.py
pastelladmin/opendata_check.py
pastelladmin/pastell_associations.py
pastelladmin/pastell_connector.py
pastelladmin/pastell_connector_instances.py
pastelladmin/pastell_docs_delete_from_list.py
pastelladmin/pastell_find.py
pastelladmin/pastell_matrice_roles.py
pastelladmin/pastell_org.py
pastelladmin/pastell_stats.py
pastelladmin/api/__init__.py
pastelladmin/api/client/__init__.py
pastelladmin/api/client/association.py
pastelladmin/api/client/connector.py
pastelladmin/api/client/document.py
pastelladmin/api/client/entity.py
pastelladmin/api/client/role.py
pastelladmin/api/client/stat.py
pastelladmin/api/client/utilisateur.py
pastelladmin/api/client/version.py
pastelladmin/shared/__init__.py
pastelladmin/shared/configuration.py
pastell_admin-0.2.0.dist-info/LICENSE
pastell_admin-0.2.0.dist-info/METADATA
pastell_admin-0.2.0.dist-info/WHEEL
pastell_admin-0.2.0.dist-info/entry_points.txt
pastell_admin-0.2.0.dist-info/top_level.txt
pastell_admin-0.2.0.dist-info/RECORD
