Metadata-Version: 2.1
Name: pastell-admin
Version: 0.2.0
Author-email: Sylvain Jolivet <sylvain.jolivet@megalis.bretagne.bzh>, Sebastien Pelhate <sebastien.pelhate@megalis.bretagne.bzh>, Yann Guenneugues <yann.guenneugues@sib.fr>
Project-URL: Homepage, https://github.com/megalis-bretagne/scripts-pastell
Project-URL: Bug Tracker, https://github.com/megalis-bretagne/scripts-pastell/issues
Classifier: Programming Language :: Python :: 3
Classifier: License :: OSI Approved :: MIT License
Classifier: Operating System :: OS Independent
Requires-Python: >=3.7
License-File: LICENSE
Requires-Dist: requests ~=2.28.1
Provides-Extra: dev
Requires-Dist: build ; extra == 'dev'
Requires-Dist: twine ; extra == 'dev'
